faddr/__init__.py
faddr/database.py
faddr/exceptions.py
faddr/faddr.py
faddr/faddr_db.py
faddr/faddr_rest.py
faddr/logging.py
faddr/models.py
faddr/parser.py
faddr/rancid.py
faddr/repo.py
faddr/results.py
faddr/schemas.py
faddr/settings.py
faddr/static/redoc.standalone.js
faddr/static/swagger-ui-bundle.js
faddr/static/swagger-ui.css
faddr/templates/cisco-ios.ttp
faddr/templates/cisco-iosxr.ttp
faddr/templates/cisco-nxos.ttp
faddr/templates/huawei-vrp.ttp
faddr/templates/juniper-junos.ttp
faddr-0.6.2.dist-info/entry_points.txt
faddr-0.6.2.dist-info/WHEEL
faddr-0.6.2.dist-info/LICENSE
faddr-0.6.2.dist-info/METADATA
faddr-0.6.2.dist-info/RECORD
